{
    "is_complete": true,
    "username": "autarklabs",
    "retweeted": {
        "1119640026063806465": {
            "id": "1119640026063806465",
            "text": "A visual summary of AGP-34  @AragonProjecthttps://www.youtube.com/watch?v=XQzgXC1L_rU&feature=youtu.be\u00a0\u2026",
            "username": "AragonBlackTeam",
            "num_likes": 44,
            "num_retweets": 20,
            "num_replies": 1
        },
        "1120653063436537856": {
            "id": "1120653063436537856",
            "text": "https://medium.com/@stellarmagnet/that-planning-suite-live-on-rinkeby-c2332e2e5e27\u00a0\u2026",
            "username": "stellarmagnet",
            "num_likes": 57,
            "num_retweets": 18,
            "num_replies": 10
        },
        "1120668923471573000": {
            "id": "1120668923471573000",
            "text": "Boom. Aragon just got another 5 apps that will take human coordination to the next level. Great work @autarklabs https://twitter.com/stellarmagnet/status/1120653063436537856\u00a0\u2026",
            "username": "licuende",
            "num_likes": 56,
            "num_retweets": 14,
            "num_replies": 0
        },
        "1100048231940136961": {
            "id": "1100048231940136961",
            "text": "Now @AragonProject has a beautiful public roadmap, finally! http://aragon.org/project/roadmap\u00a0",
            "username": "licuende",
            "num_likes": 84,
            "num_retweets": 15,
            "num_replies": 7
        },
        "1099974067317342208": {
            "id": "1099974067317342208",
            "text": "Parity & Friends meetup this Thursday in Berlin: #Substrate, @autarklabs, @pando_network, and open mic. At @fullnode_berlin. https://www.meetup.com/parity/events/259062505/\u00a0\u2026",
            "username": "ParityTech",
            "num_likes": 19,
            "num_retweets": 10,
            "num_replies": 0
        },
        "1088954048512999425": {
            "id": "1088954048512999425",
            "text": "The first AGP vote has concluded, and the results are in.\n\nAGPs\nApproved: 5, 10, 11, 12, 14, 17, 18, 19\nRejected: 16\n\nThank you to all who voted, we hope to see you all take part in the next round in Q2.\n\nhttps://mainnet.aragon.org/#/governance.aragonproject.eth/0x277bfcf7c2e162cb1ac3e9ae228a3132a75f83d4\u00a0\u2026 \u2026pic.twitter.com/7KD9p3F0ey",
            "username": "AragonProject",
            "num_likes": 42,
            "num_retweets": 8,
            "num_replies": 1
        },
        "1088842891760410627": {
            "id": "1088842891760410627",
            "text": "Awesome demo of the @autarklabs Planning Suite for @AragonProjecthttps://www.youtube.com/watch?v=ZjppWAA4Pog\u00a0\u2026",
            "username": "lkngtn",
            "num_likes": 10,
            "num_retweets": 4,
            "num_replies": 0
        },
        "1088835920936153088": {
            "id": "1088835920936153088",
            "text": "https://medium.com/@stellarmagnet/yes-on-agp-19-for-new-project-and-social-tools-in-aragon-d2fb83a3b18e\u00a0\u2026",
            "username": "stellarmagnet",
            "num_likes": 10,
            "num_retweets": 5,
            "num_replies": 0
        },
        "1088718259484995584": {
            "id": "1088718259484995584",
            "text": "Dearest $ANT holders, vote yes on AGP-19 to enable @autarklabs to continue to advance collaboration tools with @AragonProject: https://mainnet.aragon.org/#/governance.aragonproject.eth/0x277bfcf7c2e162cb1ac3e9ae228a3132a75f83d4\u00a0\u2026pic.twitter.com/Kxm12n7fte",
            "username": "AlexisAiono",
            "num_likes": 22,
            "num_retweets": 14,
            "num_replies": 2
        },
        "1086507461220229122": {
            "id": "1086507461220229122",
            "text": "ANT holders and fellow community members, @autarklabs hopes to have your vote on January 24th 00:00 UTC!\n\nFollows us @autarklabs\nRead our proposal: https://github.com/aragon/AGPs/blob/master/AGPs/AGP-19.md\u00a0\u2026\nDeliberate: https://forum.aragon.org/t/autark-flock-proposal/446\u00a0\u2026\nLive long and prosper",
            "username": "stellarmagnet",
            "num_likes": 14,
            "num_retweets": 9,
            "num_replies": 1
        },
        "1086507448154746880": {
            "id": "1086507448154746880",
            "text": "Autark (http://autark.xyz\u00a0) is our team which has a focus of equipping the @AragonProject ecosystem with tools that enable DAOs to collaborate on mega-projects to upgrade civilization. I'm excited that our Flock proposal was admitted into the ballot for next week\u2019s vote.https://twitter.com/AragonProject/status/1086308237010522113\u00a0\u2026",
            "username": "stellarmagnet",
            "num_likes": 10,
            "num_retweets": 5,
            "num_replies": 1
        }
    },
    "tweeted": {
        "1089049131144728577": {
            "id": "1089049131144728577",
            "text": "Here is a summarized version of AGP-19 which was approved for funding by the Aragon Network. We would to love to still hear feedback in the Aragon forum.https://medium.com/@stellarmagnet/autark-flock-proposal-cf19464f3129\u00a0\u2026",
            "username": "autarklabs",
            "num_likes": 10,
            "num_retweets": 3,
            "num_replies": 0
        },
        "1123253626317737984": {
            "id": "1123253626317737984",
            "text": "https://blog.autark.xyz/autark-open-work-labs-april-2019/\u00a0\u2026",
            "username": "autarklabs",
            "num_likes": 14,
            "num_retweets": 4,
            "num_replies": 0
        },
        "1110178126603186177": {
            "id": "1110178126603186177",
            "text": "https://medium.com/@stellarmagnet/autark-monthly-update-6b7b3508d69\u00a0\u2026",
            "username": "autarklabs",
            "num_likes": 13,
            "num_retweets": 3,
            "num_replies": 2
        },
        "1108343142028361728": {
            "id": "1108343142028361728",
            "text": "Autark is looking to hire a Frontend Developer w/ web3 and React expertise, that is passionate about DAOs and the future of work. Please share with your networks!https://www.autark.xyz/join\u00a0",
            "username": "autarklabs",
            "num_likes": 2,
            "num_retweets": 3,
            "num_replies": 0
        },
        "1089047638048092162": {
            "id": "1089047638048092162",
            "text": "We are so excited that AGP-19 has been officially approved. \n\nWe are looking forward to the closer collaboration with the Aragon ecosystem over the next few months.\n\nThe entire Autark team will be at #AraCon next week, see everyone in lovely Berlin!https://twitter.com/izqui9/status/1088952357394792450\u00a0\u2026",
            "username": "autarklabs",
            "num_likes": 13,
            "num_retweets": 3,
            "num_replies": 2
        },
        "1088843325321314304": {
            "id": "1088843325321314304",
            "text": "https://medium.com/@stellarmagnet/yes-on-agp-19-for-tools-to-decentralize-power-a6b56f0d2c54\u00a0\u2026",
            "username": "autarklabs",
            "num_likes": 4,
            "num_retweets": 3,
            "num_replies": 0
        }
    },
    "num_retweets_by_originator": {
        "AragonBlackTeam": 3,
        "stellarmagnet": 12,
        "licuende": 6,
        "ParityTech": 3,
        "AragonProject": 3,
        "lkngtn": 3,
        "AlexisAiono": 3
    },
    "users_retweeted": [
        "stellarmagnet",
        "licuende",
        "AragonBlackTeam",
        "ParityTech",
        "AragonProject",
        "lkngtn",
        "AlexisAiono"
    ]
}