{
    "is_complete": true,
    "username": "bingentxu",
    "retweeted": {
        "1123248698014740480": {
            "id": "1123248698014740480",
            "text": "This weeken I was invited by @geoacenter to help in a gender hackathon in Niamey. I also made #etherem masterclass to top developers in Niger. Besides the 44\u00baC and the interruptions of internet and AC, I\u2019m convinced that we will see first mass adoption in countries like Niger.pic.twitter.com/dS67HtiMIA",
            "username": "jbaylina",
            "num_likes": 38,
            "num_retweets": 11,
            "num_replies": 2
        },
        "1122170346071887873": {
            "id": "1122170346071887873",
            "text": "Aragon Network Vote #2 is now over, here's a thread with the results:https://twitter.com/AragonProject/status/1121444468979314689\u00a0\u2026",
            "username": "AragonProject",
            "num_likes": 35,
            "num_retweets": 10,
            "num_replies": 2
        },
        "1118583197040820224": {
            "id": "1118583197040820224",
            "text": "1/ Aragon 0.7 Bella is out. Check out what's new in the easiest to use Aragon release to datehttps://youtu.be/sE-9hysGc4I\u00a0",
            "username": "AragonProject",
            "num_likes": 121,
            "num_retweets": 36,
            "num_replies": 2
        },
        "1118400465925021697": {
            "id": "1118400465925021697",
            "text": "#ULTIMAHORA \nEl Open Arms tiene autorizaci\u00f3n para navegar hacia las islas de Samos y Lesbos para transportar material humanitario. \nDespu\u00e9s de 100 d\u00edas de bloqueo en puerto, podr\u00e1 zarpar. \nEso s\u00ed, seguimos sin autorizaci\u00f3n para misiones de b\u00fasqueda y rescate en el #Med central.pic.twitter.com/rC6wapt1Fn",
            "username": "openarms_fund",
            "num_likes": 3788,
            "num_retweets": 2292,
            "num_replies": 84
        },
        "1086665787065225218": {
            "id": "1086665787065225218",
            "text": "The first aragonPM hackathon is on! Come and #buidl around the @AragonProject stack to offer a decentralized alternative to #NPM. Submissions due date and winners announcement during #AraCon2019. Everything you need to know is here:https://github.com/AragonDAC/APMHackathon\u00a0\u2026",
            "username": "osarrouy",
            "num_likes": 31,
            "num_retweets": 17,
            "num_replies": 1
        },
        "1077365644058914816": {
            "id": "1077365644058914816",
            "text": "Como observador estadounidense de la pol\u00edtica espa\u00f1ola, no entiendo para que sirve el Rey. Nunca lo he entendido.\n\nImpuesto por un dictador. Esc\u00e1ndalo tras esc\u00e1ndalo. S\u00edmbolo de la desigualdad hereditaria. \u00bfPara qu\u00e9?\n\nNosotros tambi\u00e9n ten\u00edamos uno. Lo echamos en el a\u00f1o 76.\n\n1776.pic.twitter.com/U7gQzAkMjn",
            "username": "joethebrew",
            "num_likes": 19279,
            "num_retweets": 11291,
            "num_replies": 1769
        },
        "1076054957957238784": {
            "id": "1076054957957238784",
            "text": "Aragon 0.6.2 was just released! A release full of UX improvements and fixes from user feedback\n\nGiven that it was a frontend only release, all DAOs are automatically updated to 0.6.2 on both https://mainnet.aragon.org\u00a0 and https://rinkeby.aragon.org\u00a0\n\nSome highlights from this release pic.twitter.com/A9FIoQmPzn",
            "username": "AragonOneTeam",
            "num_likes": 58,
            "num_retweets": 23,
            "num_replies": 3
        },
        "1075466046373535746": {
            "id": "1075466046373535746",
            "text": "New to Solidity or brushing up on your skills? Our latest post by @bingentxu shares tips and tricks he picked up while learning how to program for #Ethereum:https://blog.aragon.one/tips-and-tricks-to-get-started-with-solidity/\u00a0\u2026",
            "username": "AragonOneTeam",
            "num_likes": 21,
            "num_retweets": 10,
            "num_replies": 0
        },
        "1070995171045793793": {
            "id": "1070995171045793793",
            "text": "Use Firefox",
            "username": "bpierre",
            "num_likes": 9,
            "num_retweets": 5,
            "num_replies": 0
        },
        "1070956084293222400": {
            "id": "1070956084293222400",
            "text": "The Aragon Conference, #AraCon2019, will bring together people who embody and wish to shape the Aragon community. Those who are building and supporting the pseudonymous, secure, trustless future. The decentralized web.\n\nCome join us!\n\nhttps://AraCon.one/\u00a0pic.twitter.com/TtAnM82TwV",
            "username": "AragonProject",
            "num_likes": 53,
            "num_retweets": 22,
            "num_replies": 1
        },
        "1067802103417135106": {
            "id": "1067802103417135106",
            "text": "Earlier this year, @AragonOneTeam was founded, @licuende resigned as the Project Lead and the Aragon Association moved to Switzerland.\n\nNow it's turn for a new cycle for the Aragon Association with @stefanobernardi as its Executive Director.https://blog.aragon.org/welcoming-stefano-to-the-aragon-association/\u00a0\u2026",
            "username": "AragonProject",
            "num_likes": 94,
            "num_retweets": 17,
            "num_replies": 5
        },
        "1060649414367293446": {
            "id": "1060649414367293446",
            "text": "Such a great and concise read on why nation states are not defensible, both from ethical and rational points of view https://pocket.co/s8CfvE\u00a0",
            "username": "licuende",
            "num_likes": 19,
            "num_retweets": 3,
            "num_replies": 3
        },
        "1055439123111182336": {
            "id": "1055439123111182336",
            "text": "Politely rejected someone and got this email  \u201cYou got me you little asian stupid cunt\u201d \n\nYou\u2019re not welcomed in crypto Sergey Kusher.pic.twitter.com/cqn0RrTayF",
            "username": "monicazng",
            "num_likes": 20,
            "num_retweets": 2,
            "num_replies": 24
        },
        "1055144100587098117": {
            "id": "1055144100587098117",
            "text": "Excited to come to #AraCon2019, but don't have the financial resources? \n\nScholarship applications for AraCon are open! We want everyone who's super interested in joining the event to be able to attend and will support them. Everyone is welcome to apply!\n\nhttps://AraCon.one/scholarships\u00a0pic.twitter.com/x84cgwEkSq",
            "username": "AragonProject",
            "num_likes": 47,
            "num_retweets": 15,
            "num_replies": 1
        },
        "1054841249763606533": {
            "id": "1054841249763606533",
            "text": "Our co-founder John Light @lightcoin has had his Twitter account suspended. He has a message to share with his friends and followers here:pic.twitter.com/hixaaxa918",
            "username": "BitseedOrg",
            "num_likes": 105,
            "num_retweets": 50,
            "num_replies": 17
        },
        "1051735289474011136": {
            "id": "1051735289474011136",
            "text": "[HILO IMPORTANTE\n[Por favor: leedlo y difundid]\n\nOs voy a contar una historia. \u00bfOs acord\u00e1is de la agresi\u00f3n de unos se\u00f1ores polic\u00edas a un vecino subsahariano en una plaza en Lavapi\u00e9s hace unos meses? Aqu\u00ed el v\u00eddeo pic.twitter.com/TADooCUpH2",
            "username": "fanetin",
            "num_likes": 3936,
            "num_retweets": 6656,
            "num_replies": 192
        },
        "1047140552137949185": {
            "id": "1047140552137949185",
            "text": "Today we\u2019re announcing the first Aragon Conference \u2014 AraCon.\n\nLearn more about #AraCon2019 in this blog post!https://blog.aragon.org/announcing-aracon-the-aragon-conference\u00a0\u2026",
            "username": "AragonProject",
            "num_likes": 192,
            "num_retweets": 60,
            "num_replies": 14
        },
        "1046803835245608960": {
            "id": "1046803835245608960",
            "text": "Just published the ETHSecurity Community Report! So many hours put in by so many people! Here's to making the Ethereum ecosystem stronger!https://medium.com/@captnseagraves/learnings-from-the-ethsecurity-community-57431ae0ed5e\u00a0\u2026",
            "username": "captnseagraves",
            "num_likes": 43,
            "num_retweets": 24,
            "num_replies": 1
        },
        "1044831856762540032": {
            "id": "1044831856762540032",
            "text": ".@goldcarESP tengo una incidencia abierta desde su aparatado de Atenci\u00f3n al Cliente y no he recibido m\u00e1s que un email autom\u00e1tico. La incidencia es por haberme cobrado 350 euros por unos da\u00f1os inexistentes en el coche.",
            "username": "Mvericat",
            "num_likes": 4,
            "num_retweets": 6,
            "num_replies": 5
        },
        "1045005457075699714": {
            "id": "1045005457075699714",
            "text": "\"It is quite rare that only that few issues are found in an Electron app, the team was\nimpressed\" -- Cure53\n\nhttps://i.kym-cdn.com/entries/icons/original/000/005/574/takemymoney.jpg\u00a0\u2026https://twitter.com/frame_eth/status/1045002222680068097\u00a0\u2026",
            "username": "sohkai",
            "num_likes": 15,
            "num_retweets": 3,
            "num_replies": 0
        },
        "1045037331923767297": {
            "id": "1045037331923767297",
            "text": "Welcome to the first Aragon community update!\n\nWe\u2019ve had a lot going on in the foreground and background of the community and on this post we go through the latest updates, like the new @RocketChat version, new community @github repository and much more!https://blog.aragon.org/aragon-community-update-1\u00a0\u2026",
            "username": "AragonProject",
            "num_likes": 29,
            "num_retweets": 10,
            "num_replies": 4
        },
        "1045002222680068097": {
            "id": "1045002222680068097",
            "text": "We've completed our first security audit conducted by @cure53berlin and funded by @AragonProject! We\u2019re happy to report the results were very positive. You can read more about it here\u2026https://medium.com/@framehq/frame-security-audit-frm-01-7a90975992af\u00a0\u2026",
            "username": "frame_eth",
            "num_likes": 30,
            "num_retweets": 12,
            "num_replies": 0
        },
        "1044291044135890944": {
            "id": "1044291044135890944",
            "text": "Another dev update! Making fast progress on our DAO features using @AragonProject! With bandwidth payments following quickly.https://medium.com/althea-mesh/althea-development-update-57-first-transactions-dao-payments-soon-to-follow-df392c792295\u00a0\u2026",
            "username": "AltheaOrg",
            "num_likes": 29,
            "num_retweets": 6,
            "num_replies": 2
        },
        "1040292464702181377": {
            "id": "1040292464702181377",
            "text": "Continuing on our Nest Team Interviews, Pando, a part of @ryhopenetwork is a decentralized and immutable versioning and cooperation system based on top of #IPFS, aragonOS and #Ethereum.\n\nRead how their team came together, what they're building and more!https://blog.aragon.org/nest-team-interviews-pando\u00a0\u2026",
            "username": "AragonProject",
            "num_likes": 48,
            "num_retweets": 14,
            "num_replies": 3
        },
        "1039881279402070016": {
            "id": "1039881279402070016",
            "text": "Announcing Aragon https://aragon.org/\u00a0 as react-springs primary sponsor.  They've been using it for their awesome aragon-ui (https://github.com/aragon/aragon-ui\u00a0\u2026) and came forward to financially support springs maintenance and longevity. Thanks @bpierre for initiating this!pic.twitter.com/fgJR5BcSAj",
            "username": "0xca0a",
            "num_likes": 55,
            "num_retweets": 9,
            "num_replies": 3
        },
        "1038198520963112961": {
            "id": "1038198520963112961",
            "text": "If you are building on Aragon at #ETHBerlin you can join our telegram channel where our team will be answering questions and helping hackers out!https://t.me/joinchat/AA_wvArD2tSfvmBJx84G4Q\u00a0\u2026",
            "username": "AragonProject",
            "num_likes": 11,
            "num_retweets": 6,
            "num_replies": 3
        },
        "1037056831879823360": {
            "id": "1037056831879823360",
            "text": "Peepeth's new crowdfunding page is live!\n\nhttps://peepeth.com/a/crowdfunding\u00a0\n\nThere, you can support with ether, tokens, and credit card.\n\nThanks for everyone's help getting Peepeth this far! ",
            "username": "peepethApp",
            "num_likes": 58,
            "num_retweets": 29,
            "num_replies": 3
        },
        "1035293708818821120": {
            "id": "1035293708818821120",
            "text": "Just merged today, the start of our local-network DAO features. Powered by @AragonProject\n\nRight now members are stored and queried. Looking to deploy the membership payment contract soon.\n\nHere's the addresses and such on the Rinkeby testnet.\n\nhttps://forum.altheamesh.com/t/blockchain-providers-sources/121\u00a0\u2026pic.twitter.com/2T2x1MbQyp",
            "username": "ttk314",
            "num_likes": 26,
            "num_retweets": 9,
            "num_replies": 1
        },
        "1032325579943669761": {
            "id": "1032325579943669761",
            "text": "It's time to hear from the astonishing Aragon Nest teams and their updates!\n\nThat Planning Suite & @ryhopenetwork on incentivization apps, @mattgcondon on an optimistic UI, @frame_eth, OS-level signing provider & @prylabs on #Ethereum 2.0 sharding clienthttps://blog.aragon.org/aragon-nest-updates-from-the-teams-q2-2018/\u00a0\u2026",
            "username": "AragonProject",
            "num_likes": 53,
            "num_retweets": 27,
            "num_replies": 4
        },
        "1029360351618498560": {
            "id": "1029360351618498560",
            "text": "You are amazing. We did it! \n\nToday, our #crowdfunding campaign comes to an end, as we reached the 250% limit. And it's all because of you!!!\nThank you for your support and for joining our journey towards a fairer tomorrow. Together #WeAreFairphone @Oneplanetcrowdpic.twitter.com/1Ug7CjYdQq",
            "username": "Fairphone",
            "num_likes": 200,
            "num_retweets": 42,
            "num_replies": 15
        },
        "1029796972650262528": {
            "id": "1029796972650262528",
            "text": "Our developers have hard at work and here's a recap of the progress of development from the second quarter of 2018.\n\nEarlier we told that first round of audits was underway and today we are also publishing the results of that audit!http://blog.aragon.org/aragon-q2-development-update\u00a0\u2026",
            "username": "AragonProject",
            "num_likes": 66,
            "num_retweets": 21,
            "num_replies": 3
        },
        "1027845522059603969": {
            "id": "1027845522059603969",
            "text": "Awesome education portal by @district0xhttps://education.district0x.io\u00a0",
            "username": "licuende",
            "num_likes": 28,
            "num_retweets": 9,
            "num_replies": 1
        },
        "1022750734536847360": {
            "id": "1022750734536847360",
            "text": "My first project into the software world was a distro to enhance Linux UX, so I'm passionate about this progress!https://ar.al/2018/07/26/popos-18.04-the-state-of-the-art-in-linux-on-desktop/\u00a0\u2026",
            "username": "licuende",
            "num_likes": 11,
            "num_retweets": 4,
            "num_replies": 0
        },
        "1022463452189605890": {
            "id": "1022463452189605890",
            "text": "\"Deploying and distributing Aragon Core\"\n\nA technical blogpost detailing how we use the Aragon Package Manager to deploy and distribute Aragon Core in a censorship-resistant manner, while keeping it accessible and with a good UX for new-comers.https://blog.aragon.one/deploying-and-distributing-aragon-core-11e70cbc9b50\u00a0\u2026",
            "username": "AragonProject",
            "num_likes": 36,
            "num_retweets": 7,
            "num_replies": 7
        },
        "1009812850049576961": {
            "id": "1009812850049576961",
            "text": "The lives of the refugees who sheltered @Snowden are in danger. Today we launch a major fundraising campaign to bring them to safety in Canada.  Please. Share this video. Together we can save 7 lives. Donate now: https://fortherefugees.com/campaigns/\u00a0 #cdnpolipic.twitter.com/6fxrufQIn9",
            "username": "4TheRefugees",
            "num_likes": 2007,
            "num_retweets": 1961,
            "num_replies": 95
        },
        "1008408350705573889": {
            "id": "1008408350705573889",
            "text": "Aragon has no airdrop and no official Telegram presence. Beware of scammers, phishing and fraud, there will never be a need to send your private key anywhere and we will never have ETH or ANT giveaways.",
            "username": "AragonProject",
            "num_likes": 48,
            "num_retweets": 13,
            "num_replies": 6
        },
        "1007220453511974912": {
            "id": "1007220453511974912",
            "text": "Fa molt bona olor. @LesMalesHerbes @Cryptshow #Purgatoripic.twitter.com/kIjHPf3wHY",
            "username": "cristianselvas",
            "num_likes": 17,
            "num_retweets": 5,
            "num_replies": 1
        },
        "1006941409788809217": {
            "id": "1006941409788809217",
            "text": "Join us in building your own customized DAO on #Ethereum!\n\nWe are opening applications for the Building #DAOs video\u00a0series where we invite teams or projects to come #buidl their customized decentralized organization together with our developers.https://blog.aragon.one/opening-applications-for-the-building-daos-video-series-81a17c92149f\u00a0\u2026",
            "username": "AragonProject",
            "num_likes": 57,
            "num_retweets": 18,
            "num_replies": 1
        },
        "1006110405650010112": {
            "id": "1006110405650010112",
            "text": "Do you like creating stunning web experiences? Join @AragonOneTeam as a web developer to make crypto less intimidating and more understandable for the masses https://wiki.aragon.one/jobs/openings/web/\u00a0\u2026",
            "username": "licuende",
            "num_likes": 28,
            "num_retweets": 16,
            "num_replies": 1
        },
        "1006111587810332672": {
            "id": "1006111587810332672",
            "text": "Have you heard about the Crypto Valley in Switzerland? Are you an efficiency radical? Do you want to travel all over the world and go to crypto events? Join @AragonOneTeam as Executive Assistant https://wiki.aragon.one/jobs/openings/exec-assistant/\u00a0\u2026 ",
            "username": "licuende",
            "num_likes": 38,
            "num_retweets": 14,
            "num_replies": 1
        },
        "1003498011144671232": {
            "id": "1003498011144671232",
            "text": "Far from a production-ready alternative to GitHub but @AragonProject Nest team @wesprdapp is working on Pando, a decentralized git repo controlled by an Aragon DAO.https://github.com/wespr/pando\u00a0",
            "username": "lightcoin",
            "num_likes": 65,
            "num_retweets": 27,
            "num_replies": 3
        },
        "1002695919274483717": {
            "id": "1002695919274483717",
            "text": "Gracias a \u00e9l se public\u00f3 la primera biograf\u00eda no autorizada del rey Juan Carlos I.pic.twitter.com/bphJZUf9Wf",
            "username": "Ahoztar1972",
            "num_likes": 11,
            "num_retweets": 15,
            "num_replies": 1
        },
        "1002277015855271937": {
            "id": "1002277015855271937",
            "text": "Today we are releasing an entirely new step for community members to signal their sentiment on the project and igniting the next level of participation in the project for all ANT holders.\n\nSurvey is the first Aragon app launched on the #Ethereum #mainnet!https://buff.ly/2suzVgP\u00a0",
            "username": "AragonProject",
            "num_likes": 165,
            "num_retweets": 64,
            "num_replies": 23
        },
        "998856748185407488": {
            "id": "998856748185407488",
            "text": "In our journey creating DAOs, we modularized components that can be used for creating mostly any dapp or protocol. We have now released incredibly convenient developer tools for builders to leverage the whole Aragon stack  #BUIDLhttps://hack.aragon.org\u00a0",
            "username": "licuende",
            "num_likes": 18,
            "num_retweets": 3,
            "num_replies": 1
        },
        "997167102883659777": {
            "id": "997167102883659777",
            "text": "We have arrived to the third entry on our Decentralizing Aragon's development series, this time talking about onboarding more new teams into working on core Aragon infrastructure.\n\nAs we told before, @AragonOneTeam is the first team, and more are coming!https://buff.ly/2rOF3N7\u00a0",
            "username": "AragonProject",
            "num_likes": 75,
            "num_retweets": 22,
            "num_replies": 10
        },
        "996808437978877953": {
            "id": "996808437978877953",
            "text": "Today, we are announcing Aragon One, the first company contributing to Aragon's development.\n\nAragon One is a for-profit company that encompasses the foundational team working and paves the way for other teams to join the core development of the project.https://buff.ly/2rN6Nku\u00a0",
            "username": "AragonProject",
            "num_likes": 136,
            "num_retweets": 43,
            "num_replies": 10
        },
        "995021955471478784": {
            "id": "995021955471478784",
            "text": "Here's our Development Update where we go through the progress from the first quarter of\u00a02018.\n\nThe biggest milestone reached was of course the release of Aragon Core v0.5, which entailed many different parts, like Radspec, aragon-ui, aragonOS, and more!\n\nhttps://buff.ly/2rxdyXA\u00a0",
            "username": "AragonProject",
            "num_likes": 67,
            "num_retweets": 21,
            "num_replies": 6
        },
        "993891944953675778": {
            "id": "993891944953675778",
            "text": "This is The Aragon Manifesto \u2013 A pledge to fight for\u00a0freedom.\n\nWe believe humankind should use technology as a liberating tool to unleash all the goodwill and creativity of our species, rather than as a tool to enslave and take advantage of one another.https://buff.ly/2K1I3wu\u00a0",
            "username": "AragonProject",
            "num_likes": 153,
            "num_retweets": 66,
            "num_replies": 8
        },
        "989941018144526336": {
            "id": "989941018144526336",
            "text": "Yes, an unconditional basic income sufficient to start everyone each month above the poverty line will most likely require more taxes in some form, BUT the amount YOUR taxes will increase is unlikely to be larger than the amount you receive in UBI, unless you're in the top 20%.pic.twitter.com/agMoOqZWIH",
            "username": "scottsantens",
            "num_likes": 229,
            "num_retweets": 144,
            "num_replies": 18
        },
        "985774873304645632": {
            "id": "985774873304645632",
            "text": "Aragon is joining http://ethtour.asia\u00a0 with @gnosisPM, @MakerDAO, @melonport & @raiden_network to meet the Asian Ethereum communities and exchange ideas. First stop, Tokyo today, come say hi!\n\nhttp://ethtour.asia\u00a0\nhttps://asia.aragon.one/\u00a0pic.twitter.com/mLX82jpSc7",
            "username": "AragonProject",
            "num_likes": 72,
            "num_retweets": 21,
            "num_replies": 5
        },
        "984374126747029505": {
            "id": "984374126747029505",
            "text": "Ja tenim la llista de guanyadors del premi Crypthow/Males Herbes 2018!!!\nhttp://lesmalesherbes.blogspot.com.es/2018/04/guanyadors-del-cryptshowmales-herbes.html\u00a0\u2026",
            "username": "LesMalesHerbes",
            "num_likes": 38,
            "num_retweets": 16,
            "num_replies": 2
        },
        "984068278933950467": {
            "id": "984068278933950467",
            "text": "\u00bfCu\u00e1l es el hilo que une una revista sat\u00edrica francesa, unas marionetas, un bar de Altsasu, un chiste de Carrero Blanco y la persecuci\u00f3n contra los CDR?pic.twitter.com/6aJpjug8go",
            "username": "jonathanmartinz",
            "num_likes": 7125,
            "num_retweets": 8602,
            "num_replies": 429
        },
        "981920484924239872": {
            "id": "981920484924239872",
            "text": "Did you already see our new video, Aragon - The fight for freedom ? This story explores the reasons why we are building Aragon and features @thegrifft, @cburniske, @Mona_El_Isa, @kennyrowe, @MihaiAlisie, @jfurgo & @FEhrsam along some Aragon team members.https://www.youtube.com/watch?v=AqjIWmiAidw\u00a0\u2026",
            "username": "AragonProject",
            "num_likes": 207,
            "num_retweets": 80,
            "num_replies": 28
        },
        "976558173619474432": {
            "id": "976558173619474432",
            "text": "Your borders, my borders\u2014 they are all just stories pic.twitter.com/5OuANQWJFG",
            "username": "medied",
            "num_likes": 10,
            "num_retweets": 4,
            "num_replies": 1
        },
        "974203914659729408": {
            "id": "974203914659729408",
            "text": "Mr @jbaylina just deployed the first @AragonProject DAO in the Ethereum mainnet. It is an Aragon Package Manager Registry that will be the backend of @DAppNODE's Docker image registry. dnp.dappnode.eth is now owned and operated by a DAO \nhttps://etherscan.io/tx/0xa1ce5838e42756070aa538b366dc2276fb4ca421f17c03d4d9e9bbe9c02e493b\u00a0\u2026",
            "username": "izqui9",
            "num_likes": 211,
            "num_retweets": 68,
            "num_replies": 8
        },
        "971541869678116864": {
            "id": "971541869678116864",
            "text": "ICOs are disruptive because they give individuals who have previously been excluded from early stage capital markets an opportunity to participate. Trying to regulate ICOs by excluding people from participating is like trying to fight piracy using DRM.",
            "username": "lkngtn",
            "num_likes": 17,
            "num_retweets": 2,
            "num_replies": 2
        },
        "971003875758141446": {
            "id": "971003875758141446",
            "text": "We sat down with @licuende @bingentxu @onordbjerg of the @aragonproject to discuss their scaling problems: Want DAOs to be deployed by people who need them, eg in poor countries where they cant afford transactions that cost $100. Also, on-chain voting hits a throughput bottleneck",
            "username": "web3foundation",
            "num_likes": 32,
            "num_retweets": 7,
            "num_replies": 2
        },
        "970730180342935553": {
            "id": "970730180342935553",
            "text": "Issue 02 of Aragon Monthly, the newspaper about #DAOs, #governance and the Aragon ecosystem has been published!\n\nCheck it out at https://buff.ly/2tgdWxV\u00a0",
            "username": "AragonProject",
            "num_likes": 64,
            "num_retweets": 25,
            "num_replies": 0
        },
        "970415789550571520": {
            "id": "970415789550571520",
            "text": "If Aaron Swartz was alive today, he'd be working on crypto.",
            "username": "licuende",
            "num_likes": 93,
            "num_retweets": 20,
            "num_replies": 5
        },
        "968435332554395648": {
            "id": "968435332554395648",
            "text": "Most importantly, it **needs** to be open source, because trust in a centralized entity is replaced for trust in the codehttps://twitter.com/lftherios/status/968425475688329222\u00a0\u2026",
            "username": "licuende",
            "num_likes": 54,
            "num_retweets": 9,
            "num_replies": 1
        },
        "964138790083231744": {
            "id": "964138790083231744",
            "text": "We are looking for a devops contractor at @AragonProject to set up some server infrastructurehttps://gist.github.com/luisivan/ee220a4202c3e8fbc0c0eca0853b6cad\u00a0\u2026",
            "username": "licuende",
            "num_likes": 16,
            "num_retweets": 7,
            "num_replies": 2
        },
        "961399108358557698": {
            "id": "961399108358557698",
            "text": "Thinking about doing the \u2018Aragon Drunk Code Review\u2019. A show in which the core team audits code for free while drinking.\n\nRT: yay\nFAV: nay",
            "username": "izqui9",
            "num_likes": 31,
            "num_retweets": 38,
            "num_replies": 9
        },
        "927857866203127808": {
            "id": "927857866203127808",
            "text": "UPDATE: For details on the security alert please read this announcement.https://paritytech.io/blog/security-alert.html\u00a0\u2026",
            "username": "ParityTech",
            "num_likes": 158,
            "num_retweets": 182,
            "num_replies": 20
        },
        "914496516810735616": {
            "id": "914496516810735616",
            "text": "Eixample - Barcelona esto es lo que hace el gobierno de Rajoy! @PPopular @PSOE @Reuters @BBCWorld @guardian @thetimes @nytimes @Mundo_ECpepic.twitter.com/nCMnDqVX5G",
            "username": "juli15apac",
            "num_likes": 1,
            "num_retweets": 2,
            "num_replies": 0
        },
        "909082872996356096": {
            "id": "909082872996356096",
            "text": "Can't put into words how ashamed I am as a spaniard https://twitter.com/celeduc/status/909080178038583296\u00a0\u2026",
            "username": "izqui9",
            "num_likes": 34,
            "num_retweets": 9,
            "num_replies": 4
        },
        "897974075347173376": {
            "id": "897974075347173376",
            "text": "Twitter's in no danger - it has network effects. But social media is too important to humanity to leave as a walled garden forever.https://twitter.com/coindesk/status/897900114223693829\u00a0\u2026",
            "username": "naval",
            "num_likes": 648,
            "num_retweets": 183,
            "num_replies": 42
        },
        "885553091466186754": {
            "id": "885553091466186754",
            "text": "Want to know what it's like to work at Volta? Check our our blog post https://voltanet.io/day-office-hiring/\u00a0\u2026 to find out how to join us! #rethinknetworking",
            "username": "voltanetworks",
            "num_likes": 2,
            "num_retweets": 1,
            "num_replies": 0
        },
        "885100007749287936": {
            "id": "885100007749287936",
            "text": "#NetNeutrality allowed me to invent the web without having to ask for permission. Let's keep the internet open!http://battleforthenet.com\u00a0",
            "username": "timberners_lee",
            "num_likes": 24122,
            "num_retweets": 24532,
            "num_replies": 254
        },
        "883923159291920384": {
            "id": "883923159291920384",
            "text": " News & Blog: Packet Pushers - Blogs Startup Radar: Volta Networks Puts The Router Control Plane In The Cloud - http://tracking.feedpress.i",
            "username": "packetpushers",
            "num_likes": 2,
            "num_retweets": 1,
            "num_replies": 0
        },
        "877674563651473408": {
            "id": "877674563651473408",
            "text": "Debit side's PayPal as we call them is the honoree @sezzleinc who are saving us all from checkbook madness! Congrats! #MSPBJeurekapic.twitter.com/T4CpOxtMgh",
            "username": "MSPBJevents",
            "num_likes": 6,
            "num_retweets": 1,
            "num_replies": 0
        },
        "871794375751331840": {
            "id": "871794375751331840",
            "text": "@voltanetworks is at @nanog in Bellevue. #rethinknetworkingpic.twitter.com/JgQWFNRNgJ",
            "username": "voltanetworks",
            "num_likes": 2,
            "num_retweets": 2,
            "num_replies": 0
        },
        "869104030571790336": {
            "id": "869104030571790336",
            "text": "Monaco VISA\u00ae Card brings crypto token spending to the masses.ICO is LIVE NOW. https://goo.gl/ZsdCbO\u00a0pic.twitter.com/tB8SVBRC5I",
            "username": "RealTimeCrypto",
            "num_likes": 53,
            "num_retweets": 34,
            "num_replies": 1
        },
        "869229023431462913": {
            "id": "869229023431462913",
            "text": "We're very excited to introduce The Status Network, and a upcoming Contribution Period slated for June 17th 2017: https://blog.status.im/announcing-the-status-network-c6dd18e770e\u00a0\u2026pic.twitter.com/SmhWTolZlw",
            "username": "ethstatus",
            "num_likes": 146,
            "num_retweets": 100,
            "num_replies": 11
        },
        "859108522319114240": {
            "id": "859108522319114240",
            "text": "See our latest blog post on Free Range Routing: http://voltanet.io/free-range-routing/\u00a0\u2026pic.twitter.com/Hr91yHcKC3",
            "username": "voltanetworks",
            "num_likes": 0,
            "num_retweets": 3,
            "num_replies": 0
        },
        "849036760768065536": {
            "id": "849036760768065536",
            "text": "Welcome FRRouting members @6WINDsoftware Architecture Tech Corp @bigswitch @Orange @CumulusNetworks LabN Consulting NetDEF & @voltanetworks!",
            "username": "linuxfoundation",
            "num_likes": 8,
            "num_retweets": 9,
            "num_replies": 1
        },
        "851486685749805056": {
            "id": "851486685749805056",
            "text": "You can watch Volta's Marc Su\u00f1\u00e9 present The Disaggregated Router at ESNOG in Barcelona at https://lnkd.in/dHJBFSU\u00a0 #rethinkroutingpic.twitter.com/0voTefwjx1",
            "username": "voltanetworks",
            "num_likes": 0,
            "num_retweets": 1,
            "num_replies": 0
        },
        "848658687505960961": {
            "id": "848658687505960961",
            "text": "#FRRouting Proud to announce 2.0 https://github.com/FRRouting/frr/releases/tag/frr-2.0\u00a0\u2026\nI would really like to thank everyone who participated",
            "username": "menotyousharp",
            "num_likes": 11,
            "num_retweets": 5,
            "num_replies": 0
        },
        "844239183627649025": {
            "id": "844239183627649025",
            "text": "Added a Label Manager to #FRR to allow the routing daemons to share label space amongst themselves.https://github.com/freerangerouting/frr\u00a0\u2026",
            "username": "menotyousharp",
            "num_likes": 2,
            "num_retweets": 1,
            "num_replies": 0
        },
        "834737036972216320": {
            "id": "834737036972216320",
            "text": "I\u00f1aki Urdangarin y su entrada en prisi\u00f3npic.twitter.com/r4aR36gDcT",
            "username": "MuyNunez",
            "num_likes": 9650,
            "num_retweets": 14146,
            "num_replies": 83
        },
        "828025943163822081": {
            "id": "828025943163822081",
            "text": "Mirad lo RECAUDADO por estas pel\u00edculas. \n30 euros, 6 euros...!!! \nSe comenta solo. \n#BoicotALosGoya #goya2017pic.twitter.com/wv5wegbOaN",
            "username": "lady_cramerick",
            "num_likes": 149,
            "num_retweets": 216,
            "num_replies": 29
        },
        "827455369500823552": {
            "id": "827455369500823552",
            "text": "Contribuyamos entre todxs a evitar malos rollos con estas pastillas. Difunde con un RT esta alerta: https://energycontrol.org/analisis-de-sustancias/resultados/alertas/616-alfa-pvp-flakka-vendido-como-pastilla-de-mdma.html\u00a0\u2026 #AlertaECpic.twitter.com/B5g7PstaTR",
            "username": "EC_es",
            "num_likes": 4,
            "num_retweets": 18,
            "num_replies": 0
        },
        "781811372166381568": {
            "id": "781811372166381568",
            "text": "Celebrating 2 weeks of our podcast in style by giving away a huge Buffer Swag pack!  RT this for a chance to win!  http://buff.ly/2dD8Y2z\u00a0pic.twitter.com/YNQts7mxcb",
            "username": "buffer",
            "num_likes": 188,
            "num_retweets": 392,
            "num_replies": 41
        },
        "776434280180310016": {
            "id": "776434280180310016",
            "text": "A bit of nostalgia... Platina @xavierlanau \u200b mix 22/09/2008 Setting Standards\nhttps://www.mixcloud.com/KilltheDJbcn/platina-mix-22092008-setting-standards/\u00a0\u2026pic.twitter.com/mEmPEkpFkj",
            "username": "KilltheDjBCN",
            "num_likes": 3,
            "num_retweets": 3,
            "num_replies": 0
        },
        "733046996756496386": {
            "id": "733046996756496386",
            "text": "Beautiful. https://vimeo.com/163153865\u00a0.",
            "username": "BenLaurie",
            "num_likes": 2,
            "num_retweets": 1,
            "num_replies": 0
        },
        "730708745722966017": {
            "id": "730708745722966017",
            "text": "\u00bfC\u00f3mo sobrevivi\u00f3 la humanidad hace 10.000 a\u00f1os?Un v\u00eddeo recrea la lucha por la supervivencia http://ow.ly/XkN730089xa\u00a0pic.twitter.com/4NmgMfa1mB",
            "username": "BSC_CNS",
            "num_likes": 10,
            "num_retweets": 12,
            "num_replies": 1
        },
        "688329129654120448": {
            "id": "688329129654120448",
            "text": "Ni\u00f1o Becerra: \"el petr\u00f3leo alcanzar\u00e1 los 250 d\u00f3lares en el a\u00f1o 2015\". http://www.invertia.com/noticias/articulo-final.asp?idNoticia=2129553\u00a0\u2026",
            "username": "Noatodo",
            "num_likes": 26,
            "num_retweets": 45,
            "num_replies": 6
        },
        "694132042150318080": {
            "id": "694132042150318080",
            "text": "Dejo Men\u00e9ame, tiene nuevos administradores y CEO. Gracias por la marcha estos 10 a\u00f1os. http://blog.meneame.net/2016/02/01/una-nueva-etapa-para-meneame/\u00a0\u2026",
            "username": "gallir",
            "num_likes": 143,
            "num_retweets": 246,
            "num_replies": 67
        },
        "616610630775271424": {
            "id": "616610630775271424",
            "text": "Congrats @__Passport__ on cover of @parkingtoday. #CLT #Entrepreneurial #SuccessStory. @cltmayor @drainey1 http://www.parkingtoday.com/3D/parkingtoday-jul2015/index.html\u00a0\u2026",
            "username": "danielroselli",
            "num_likes": 9,
            "num_retweets": 10,
            "num_replies": 0
        },
        "531823010572169216": {
            "id": "531823010572169216",
            "text": "Are you part of #TeamVirunga? Find out on #Netflix: http://www.netflix.com/WiMovie/80009431\u00a0\u2026pic.twitter.com/BnjLhLJ8f1",
            "username": "virungamovie",
            "num_likes": 121,
            "num_retweets": 237,
            "num_replies": 11
        }
    },
    "tweeted": {
        "1083064563094966273": {
            "id": "1083064563094966273",
            "text": "Less than 3 weeks for AraCon! Don't miss it. Now you can use this code for a 30% discount!\nhttps://ti.to/aragon/aracon-one/discount/ARAGONONE\u00a0\u2026",
            "username": "bingentxu",
            "num_likes": 5,
            "num_retweets": 0,
            "num_replies": 0
        },
        "1073165827640307712": {
            "id": "1073165827640307712",
            "text": "Mi madre nunca quiso vivir as\u00ed. DESPENALIZAR LA EUTANASIA y el suicidio m\u00e9dico asistido. @sanidadgob @luisacarcedo - \u00a1Firma la petici\u00f3n! http://chng.it/XkVNjb2y\u00a0 via @change_es",
            "username": "bingentxu",
            "num_likes": 0,
            "num_retweets": 0,
            "num_replies": 0
        },
        "1063555793444839424": {
            "id": "1063555793444839424",
            "text": "Hace unos meses tuve otro siniestro, el viento me rasg\u00f3 unos estores exteriores de las ventanas. Tampoco me cubrieron. Ni siquiera se dignaron a explicarme por qu\u00e9. En ambos casos me hicieron perder el tiempo mandando fotos, documentaci\u00f3n, etc. Lamentable @nn_espana",
            "username": "bingentxu",
            "num_likes": 0,
            "num_retweets": 0,
            "num_replies": 0
        },
        "1063555010548719616": {
            "id": "1063555010548719616",
            "text": "Tengo dos seguros de hogar con @nn_espana Esta semana me han entrado a robar en uno de ellos y me dicen que no me cubren porque no estoy empadronado all\u00ed. Si s\u00f3lo puedo estar empadronado en un sitio, por qu\u00e9 me cobran dos p\u00f3lizas?",
            "username": "bingentxu",
            "num_likes": 0,
            "num_retweets": 2,
            "num_replies": 1
        },
        "1055149541601755137": {
            "id": "1055149541601755137",
            "text": "Requesting faucet funds into 0x9b844F5C5f5Ece8209f6bfb9364953d9E723286E on the #Rinkeby #Ethereum test network.",
            "username": "bingentxu",
            "num_likes": 1,
            "num_retweets": 0,
            "num_replies": 0
        },
        "1045241313841598464": {
            "id": "1045241313841598464",
            "text": "Requesting faucet funds into 0x2b908c4F0353245775C085e7050ab4583Eae5b16 on the #Rinkeby #Ethereum test network.",
            "username": "bingentxu",
            "num_likes": 7,
            "num_retweets": 0,
            "num_replies": 0
        },
        "1031932379164749824": {
            "id": "1031932379164749824",
            "text": "I just backed Peepeth \u2014 Social Network For A Better World on @Kickstarterhttp://kck.st/2N7Xh5a\u00a0",
            "username": "bingentxu",
            "num_likes": 10,
            "num_retweets": 0,
            "num_replies": 0
        },
        "1017896357749755904": {
            "id": "1017896357749755904",
            "text": "Este refer\u00e9ndum es un sue\u00f1o que llevamos a\u00f1os persiguiendo. Los Borbones se han hecho ricos a nuestra costa. \u00bfNo crees que ha llegado la hora de decir \u201cbasta\u201d? \u00a1Firma y difunde la petici\u00f3n ahora! @publico_eshttp://bit.ly/2mgav3Z\u00a0",
            "username": "bingentxu",
            "num_likes": 2,
            "num_retweets": 0,
            "num_replies": 1
        },
        "1014408212525780992": {
            "id": "1014408212525780992",
            "text": "I just helped to stop #CensorshipMachines that would filter ALL of our online content. You too can help to #SaveYourInternet: http://d.shpg.org/424272689t\u00a0 Contact your EU representative before 5 July!",
            "username": "bingentxu",
            "num_likes": 3,
            "num_retweets": 0,
            "num_replies": 0
        },
        "1008607824790872065": {
            "id": "1008607824790872065",
            "text": "The EU #copyright reform threatens Free and Open Source Software. Sign the open letter and #savecodeshare!https://savecodeshare.eu/\u00a0",
            "username": "bingentxu",
            "num_likes": 2,
            "num_retweets": 0,
            "num_replies": 0
        },
        "986680413421821953": {
            "id": "986680413421821953",
            "text": "Verifying my identity on http://Peepeth.com\u00a0 0x213de3994517a65ef92c7ad4ec9b824dcccc67f5",
            "username": "bingentxu",
            "num_likes": 0,
            "num_retweets": 0,
            "num_replies": 0
        },
        "965992715358998529": {
            "id": "965992715358998529",
            "text": "Ironically, it was #crypto which led me to a heavy use of Twitter and Medium. Unfortunately, I don't think I'll see the crypto community on @MastodonProject, so waiting for more luck with @LeeroyNetwork or similar.",
            "username": "bingentxu",
            "num_likes": 4,
            "num_retweets": 0,
            "num_replies": 1
        },
        "965992713433899008": {
            "id": "965992713433899008",
            "text": "I was a decentralization lover long before [https://steemit.com/raspberrypi/@bingen/docker-home-server-for-raspberry-pi\u00a0\u2026] the blockchain boom. That's why I tried to use things like http://identi.ca\u00a0, @joindiaspora or @WordPress instead of garden wallets.",
            "username": "bingentxu",
            "num_likes": 5,
            "num_retweets": 0,
            "num_replies": 1
        },
        "963702056610562048": {
            "id": "963702056610562048",
            "text": "Requesting faucet funds into 0xbFdECf1Db5c22d4CD3B0Bb970cF867BEFd2caE27 on the #Rinkeby #Ethereum test network.",
            "username": "bingentxu",
            "num_likes": 3,
            "num_retweets": 0,
            "num_replies": 2
        },
        "953533041514827776": {
            "id": "953533041514827776",
            "text": "If it is public money, it should be public code as well! I support @fsfe's call for more #publiccode: https://publiccode.eu/\u00a0",
            "username": "bingentxu",
            "num_likes": 3,
            "num_retweets": 0,
            "num_replies": 1
        },
        "926010335756201985": {
            "id": "926010335756201985",
            "text": "For people outside my network that want to get in touch with me, I can now be reached athttp://Earn.com/bingen\u00a0",
            "username": "bingentxu",
            "num_likes": 2,
            "num_retweets": 0,
            "num_replies": 0
        },
        "922498272790564865": {
            "id": "922498272790564865",
            "text": "Pay what you want for Bitcoin, blockchain, and cryptocurrency books and support charity! https://www.humblebundle.com/books/bitcoin-cryptocurrency-books\u00a0\u2026 via @humblebooks",
            "username": "bingentxu",
            "num_likes": 0,
            "num_retweets": 0,
            "num_replies": 0
        },
        "893117229411205120": {
            "id": "893117229411205120",
            "text": "Blockchain: the solution for transparency in product supply chains on @ProvenanceHQhttps://www.provenance.org/whitepaper\u00a0",
            "username": "bingentxu",
            "num_likes": 1,
            "num_retweets": 0,
            "num_replies": 0
        },
        "887426214008418306": {
            "id": "887426214008418306",
            "text": "A Virtual Private Home Server with e-mail, @Nextclouders and more using #Docker Swarm and #RaspberryPihttps://steemit.com/raspberrypi/@bingen/docker-home-server-for-raspberry-pi\u00a0\u2026",
            "username": "bingentxu",
            "num_likes": 9,
            "num_retweets": 2,
            "num_replies": 1
        },
        "849004422499794944": {
            "id": "849004422499794944",
            "text": "Apadrina un l\u00fapulohttps://www.verkami.com/locale/en/projects/16618-apadrina-un-lupulo\u00a0\u2026",
            "username": "bingentxu",
            "num_likes": 0,
            "num_retweets": 0,
            "num_replies": 0
        },
        "828877001197047808": {
            "id": "828877001197047808",
            "text": "Conviene recordar algunos datos sobre la propiedad intelectual y la ley Sinde https://gallir.wordpress.com/2011/12/26/conviene-recordar-sobre-la-propiedad-intelectual-y-la-ley-sinde/\u00a0\u2026 via @gallir #BoicotALosGoya",
            "username": "bingentxu",
            "num_likes": 0,
            "num_retweets": 0,
            "num_replies": 0
        },
        "815362146993315840": {
            "id": "815362146993315840",
            "text": "#fregonahit No, I won't, no, I won't... @AlbertLuengo",
            "username": "bingentxu",
            "num_likes": 1,
            "num_retweets": 0,
            "num_replies": 1
        },
        "815361788367794176": {
            "id": "815361788367794176",
            "text": "#fregonahit Lips Inc., Funky Town",
            "username": "bingentxu",
            "num_likes": 0,
            "num_retweets": 0,
            "num_replies": 0
        },
        "815356116792004608": {
            "id": "815356116792004608",
            "text": "https://www.pscp.tv/w/azb1LDM1MzE4OTR8MU95S0FBdkVXTXdLYhA0QAVfA82uoS_Bs2Aq_uU982e7KIDygaX_mSxK7GfU\u00a0\u2026",
            "username": "bingentxu",
            "num_likes": 2,
            "num_retweets": 0,
            "num_replies": 0
        },
        "815351037511008256": {
            "id": "815351037511008256",
            "text": "#fregonahit An der beat Knuf!",
            "username": "bingentxu",
            "num_likes": 1,
            "num_retweets": 0,
            "num_replies": 0
        },
        "765573835827601408": {
            "id": "765573835827601408",
            "text": "\u00a1Paremos la primera mina en el fondo del mar! @loews_hotels y @metalloinvest, acaben con este peligroso negocio https://secure.avaaz.org/es/png_nautilus_sust/?wBjaGab\u00a0\u2026",
            "username": "bingentxu",
            "num_likes": 0,
            "num_retweets": 0,
            "num_replies": 0
        },
        "763463986159427585": {
            "id": "763463986159427585",
            "text": "I love Brava Fabrics. Use my referral link to get a discount now! http://bravafabrics.refr.cc/BR2Z2MQ\u00a0",
            "username": "bingentxu",
            "num_likes": 0,
            "num_retweets": 0,
            "num_replies": 0
        },
        "750414506468184064": {
            "id": "750414506468184064",
            "text": "Verifying myself: I am bingen on Keybase.io. pr51cNFE2JevDy5tAa8VeCCzmu-4jLprsagx / https://keybase.io/bingen/sigs/pr51cNFE2JevDy5tAa8VeCCzmu-4jLprsagx\u00a0\u2026",
            "username": "bingentxu",
            "num_likes": 0,
            "num_retweets": 0,
            "num_replies": 0
        },
        "686951149564473344": {
            "id": "686951149564473344",
            "text": "Hacking Gmail to use custom domains for free | Simply Ian https://simplyian.com/2015/01/07/Hacking-GMail-to-use-custom-domains-for-free/\u00a0\u2026",
            "username": "bingentxu",
            "num_likes": 1,
            "num_retweets": 0,
            "num_replies": 0
        },
        "634750835705151489": {
            "id": "634750835705151489",
            "text": "So cool:  http://stackoverflow.com/10m\u00a0 #SOreadytohelp",
            "username": "bingentxu",
            "num_likes": 0,
            "num_retweets": 0,
            "num_replies": 0
        },
        "614068467638124544": {
            "id": "614068467638124544",
            "text": "Hey @opensourceway, I'd like a chance to win a copy of Mastering Emacs from your summer reading list: http://red.ht/1CnZBsg\u00a0 #OSSReads",
            "username": "bingentxu",
            "num_likes": 0,
            "num_retweets": 0,
            "num_replies": 0
        },
        "609280304218554368": {
            "id": "609280304218554368",
            "text": "Interesting job at an awesome company:\nhttps://www.linkedin.com/jobs2/cap/view/55459161\u00a0\u2026",
            "username": "bingentxu",
            "num_likes": 0,
            "num_retweets": 0,
            "num_replies": 0
        },
        "585436406396387328": {
            "id": "585436406396387328",
            "text": "Happy to be the 1,003rd backer on @BackerKit for Flutter: Low cost wireless pr... | Thx @FlutterWireless! https://flutterwireless.backerkit.com/hosted_preorders/backers/433154\u00a0\u2026",
            "username": "bingentxu",
            "num_likes": 1,
            "num_retweets": 0,
            "num_replies": 0
        },
        "579216985491398657": {
            "id": "579216985491398657",
            "text": "http://html5drummachine.com/\u00a0",
            "username": "bingentxu",
            "num_likes": 0,
            "num_retweets": 0,
            "num_replies": 0
        },
        "529343720185810944": {
            "id": "529343720185810944",
            "text": "\u00a1He descargado gratis la gu\u00eda del aut\u00f3nomo de @txerpa!https://txerpa.com\u00a0",
            "username": "bingentxu",
            "num_likes": 0,
            "num_retweets": 2,
            "num_replies": 1
        },
        "462705194275713024": {
            "id": "462705194275713024",
            "text": "#penyaHumphrey test",
            "username": "bingentxu",
            "num_likes": 0,
            "num_retweets": 0,
            "num_replies": 0
        },
        "306813829969498112": {
            "id": "306813829969498112",
            "text": "Listening to the pH sessions room on @soundrop. Join us now! http://open.soundrop.fm/s/WfqzywyMUb6ksGNZ\u00a0\u2026",
            "username": "bingentxu",
            "num_likes": 0,
            "num_retweets": 0,
            "num_replies": 0
        },
        "306813013493686272": {
            "id": "306813013493686272",
            "text": "Listening to the PassportParking room with 2 others on @soundrop. Join us now! http://open.soundrop.fm/s/WfCS4hcTJnobrZBg\u00a0\u2026",
            "username": "bingentxu",
            "num_likes": 0,
            "num_retweets": 0,
            "num_replies": 0
        }
    },
    "not_retweeted": {},
    "num_retweets_by_originator": {
        "jbaylina": 1,
        "AragonProject": 22,
        "openarms_fund": 1,
        "osarrouy": 1,
        "joethebrew": 1,
        "AragonOneTeam": 2,
        "bpierre": 1,
        "licuende": 9,
        "monicazng": 1,
        "BitseedOrg": 1,
        "fanetin": 1,
        "captnseagraves": 1,
        "Mvericat": 1,
        "sohkai": 1,
        "frame_eth": 1,
        "AltheaOrg": 1,
        "0xca0a": 1,
        "peepethApp": 1,
        "ttk314": 1,
        "Fairphone": 1,
        "4TheRefugees": 1,
        "cristianselvas": 1,
        "lightcoin": 1,
        "Ahoztar1972": 1,
        "scottsantens": 1,
        "LesMalesHerbes": 1,
        "jonathanmartinz": 1,
        "medied": 1,
        "izqui9": 3,
        "lkngtn": 1,
        "web3foundation": 1,
        "ParityTech": 1,
        "juli15apac": 1,
        "naval": 1,
        "voltanetworks": 4,
        "timberners_lee": 1,
        "packetpushers": 1,
        "MSPBJevents": 1,
        "RealTimeCrypto": 1,
        "ethstatus": 1,
        "linuxfoundation": 1,
        "menotyousharp": 2,
        "MuyNunez": 1,
        "lady_cramerick": 1,
        "EC_es": 1,
        "buffer": 1,
        "KilltheDjBCN": 1,
        "BenLaurie": 1,
        "BSC_CNS": 1,
        "Noatodo": 1,
        "gallir": 1,
        "danielroselli": 1,
        "virungamovie": 1
    },
    "users_retweeted": [
        "AragonProject",
        "licuende",
        "voltanetworks",
        "izqui9",
        "AragonOneTeam",
        "menotyousharp",
        "jbaylina",
        "openarms_fund",
        "osarrouy",
        "joethebrew",
        "bpierre",
        "monicazng",
        "BitseedOrg",
        "fanetin",
        "captnseagraves",
        "Mvericat",
        "sohkai",
        "frame_eth",
        "AltheaOrg",
        "0xca0a",
        "peepethApp",
        "ttk314",
        "Fairphone",
        "4TheRefugees",
        "cristianselvas",
        "lightcoin",
        "Ahoztar1972",
        "scottsantens",
        "LesMalesHerbes",
        "jonathanmartinz",
        "medied",
        "lkngtn",
        "web3foundation",
        "ParityTech",
        "juli15apac",
        "naval",
        "timberners_lee",
        "packetpushers",
        "MSPBJevents",
        "RealTimeCrypto",
        "ethstatus",
        "linuxfoundation",
        "MuyNunez",
        "lady_cramerick",
        "EC_es",
        "buffer",
        "KilltheDjBCN",
        "BenLaurie",
        "BSC_CNS",
        "Noatodo",
        "gallir",
        "danielroselli",
        "virungamovie"
    ]
}