{"users_retweeted": ["SteveNash", "dmorey", "Thouxanbanronny"], "tweeted": {"1123266584934588416": {"num_replies": 1, "num_retweets": 25, "username": "sportspickle", "id": "1123266584934588416", "num_likes": 111, "text": "This level of comedy is worth the price of a subscription.https://twitter.com/TheAthletic/status/1123259396996263938\u00a0\u2026"}, "1122165887459627009": {"num_replies": 5, "num_retweets": 153, "username": "sportspickle", "id": "1122165887459627009", "num_likes": 929, "text": "Seeing lots of reports of GMs and coaches being very high on the players they drafted. Smart of them not to draft guys they think suck at football. Now I understand how they got so far in their profession."}, "1122270321602646016": {"num_replies": 6, "num_retweets": 15, "username": "sportspickle", "id": "1122270321602646016", "num_likes": 205, "text": "Here are all the grades for the 2019 NFL Draft:\n\nA \n\nB\n\nC\n\nD\n\nF"}, "1121936957653880833": {"num_replies": 2, "num_retweets": 68, "username": "sportspickle", "id": "1121936957653880833", "num_likes": 329, "text": "DK Metcalf's slide is EXACTLY why I've always made sure not to workout too much."}, "1121569373158875140": {"num_replies": 0, "num_retweets": 6, "username": "sportspickle", "id": "1121569373158875140", "num_likes": 35, "text": "The Oakland A's are Kyler Murray hipsters."}, "1121937352094621698": {"num_replies": 2, "num_retweets": 15, "username": "sportspickle", "id": "1121937352094621698", "num_likes": 110, "text": "Tyler Eifert just broke his thumbs unfollowing the Bengals."}, "1121927481961922562": {"num_replies": 0, "num_retweets": 8, "username": "sportspickle", "id": "1121927481961922562", "num_likes": 52, "text": "Employing Joe Flacco is one of the top reasons NFL teams use early draft picks on quarterbacks."}, "1121935218447998978": {"num_replies": 0, "num_retweets": 7, "username": "sportspickle", "id": "1121935218447998978", "num_likes": 32, "text": "It would be very NFL if Tyreek Hill gets released the same day Jim Brown is invited to announce a draft pick."}, "1121581557305757696": {"num_replies": 3, "num_retweets": 49, "username": "sportspickle", "id": "1121581557305757696", "num_likes": 336, "text": "When you find out he is even worse than you.pic.twitter.com/wkqJzlsKlJ"}, "1123049331265814529": {"num_replies": 0, "num_retweets": 11, "username": "sportspickle", "id": "1123049331265814529", "num_likes": 95, "text": "I know when I see a good sports play, I immediately think: but what did Drake think about it? \n\nThankfully, sports TV always lets me know."}, "1122945444055793665": {"num_replies": 2, "num_retweets": 14, "username": "sportspickle", "id": "1122945444055793665", "num_likes": 85, "text": "Warriors: \"No team could be more unlikable than us.\" \n\nRockets: \"Hold my audit.\"http://www.espn.com/nba/story/_/id/26634745/rockets-audited-18-game-7-say-finals-bid-taken\u00a0\u2026"}, "1121590740579229696": {"num_replies": 2, "num_retweets": 7, "username": "sportspickle", "id": "1121590740579229696", "num_likes": 83, "text": "Dolphins are all-in on tanking, so they'll select the worst player available here. Congratulations to new NFL player Darren Rovell."}, "1121932762490048512": {"num_replies": 4, "num_retweets": 19, "username": "sportspickle", "id": "1121932762490048512", "num_likes": 162, "text": "There have now been 62 trades in the first 45 picks of the draft. Congratulations to everyone who spent months churning out mock drafts. A life well-lived."}, "1121579698776158209": {"num_replies": 3, "num_retweets": 27, "username": "sportspickle", "id": "1121579698776158209", "num_likes": 136, "text": "Pick is in. The New York Giants are drafting Cooper Manning."}, "1121581342297350144": {"num_replies": 3, "num_retweets": 16, "username": "sportspickle", "id": "1121581342297350144", "num_likes": 149, "text": "When your team drafts your replacement.pic.twitter.com/m9oioMSBLu"}, "1122273864321519616": {"num_replies": 4, "num_retweets": 62, "username": "sportspickle", "id": "1122273864321519616", "num_likes": 383, "text": "Ten years ago, Kyler Murray wouldn't have been drafted at all, while a team would have talked themselves into Tyree Jackson in the 1st Round because he is tall. \n\nMy point is this: it would have been dumb to draft either of them then because they were like 10 years old."}, "1121572695840362497": {"num_replies": 4, "num_retweets": 90, "username": "sportspickle", "id": "1121572695840362497", "num_likes": 301, "text": "Nick Bosa is the highest player ever drafted from the Confederacy."}}, "username": "sportspickle", "in_network": false, "retweeted": {"1121943189210820608": {"num_replies": 14, "num_retweets": 1, "username": "Thouxanbanronny", "id": "1121943189210820608", "num_likes": 20, "text": "What? always spectators with the dumb ass comments mf probably run a 5.5https://twitter.com/sportspickle/status/1121936957653880833\u00a0\u2026"}, "1122166859871207424": {"num_replies": 52, "num_retweets": 393, "username": "dmorey", "id": "1122166859871207424", "num_likes": 4220, "text": "Be patient - there is a learning curve on this. For a few years we tried drafting players we thought were terrible but it didn't work out for us so we went back to drafting players we thought were good at basketball.https://twitter.com/sportspickle/status/1122165887459627009\u00a0\u2026"}, "1121986968152207360": {"num_replies": 752, "num_retweets": 19857, "username": "SteveNash", "id": "1121986968152207360", "num_likes": 114496, "text": "Kevin Durant\u2019s 38 pts in the half of a playoff game are 3 more than steve nash\u2019s 35 in 2005 vs Dallas. It\u2019s not nearly as impressive though because there are more possessions in today\u2019s game. And because Kevin Durant is taller and better at basketball."}}, "is_complete": false, "not_retweeted": {}, "num_retweets_by_originator": {"SteveNash": 1, "dmorey": 1, "Thouxanbanronny": 1}}